{
  "id" : "stg_customers",
  "metainfo" : {
    "label" : "stg_customers",
    "autoLayout" : true,
    "staleState" : "none",
    "sourceSuggestions" : {
      "sources" : [ ]
    },
    "graphConfig" : {
      "userDefinedConfig" : {
        "vars" : { }
      }
    }
  },
  "processes" : {
    "source##YPp8aK9U" : {
      "id" : "source##YPp8aK9U",
      "component" : "Seed",
      "metadata" : {
        "label" : "source",
        "phase" : 0,
        "comment" : "-\n    Normally we would select from the table here, but we are using seeds to load\n    our data in this project\n    "
      },
      "properties" : {
        "table" : {
          "name" : "raw_customers",
          "sourceType" : "Seed"
        }
      },
      "ports" : {
        "inputs" : [ ],
        "outputs" : [ {
          "id" : "SAWHdZ01",
          "schema" : {
            "providerType" : "Databricks",
            "fields" : [ {
              "name" : "id",
              "dataType" : {
                "type" : "Integer"
              }
            }, {
              "name" : "first_name",
              "dataType" : {
                "type" : "String"
              }
            }, {
              "name" : "last_name",
              "dataType" : {
                "type" : "String"
              }
            } ]
          },
          "slug" : "out"
        } ],
        "isCustomOutputSchema" : false
      }
    },
    "renamed##udGLOQOW" : {
      "id" : "renamed##udGLOQOW",
      "component" : "Reformat",
      "metadata" : {
        "label" : "renamed",
        "phase" : 0,
        "macroDependencies" : [ ]
      },
      "properties" : {
        "columnsSelector" : [ "KFQY13U2##id", "KFQY13U2##first_name", "KFQY13U2##last_name" ],
        "expressions" : [ {
          "expression" : {
            "expression" : "id"
          },
          "alias" : "customer_id"
        }, {
          "expression" : {
            "expression" : "first_name"
          }
        }, {
          "expression" : {
            "expression" : "last_name"
          }
        } ]
      },
      "ports" : {
        "inputs" : [ {
          "id" : "KFQY13U2",
          "schema" : {
            "providerType" : "Databricks",
            "fields" : [ {
              "name" : "id",
              "dataType" : {
                "type" : "Integer"
              }
            }, {
              "name" : "first_name",
              "dataType" : {
                "type" : "String"
              }
            }, {
              "name" : "last_name",
              "dataType" : {
                "type" : "String"
              }
            } ]
          },
          "slug" : "source"
        } ],
        "outputs" : [ {
          "id" : "DUTyumng",
          "schema" : {
            "providerType" : "Databricks",
            "fields" : [ {
              "name" : "customer_id",
              "dataType" : {
                "type" : "Integer"
              }
            }, {
              "name" : "first_name",
              "dataType" : {
                "type" : "String"
              }
            }, {
              "name" : "last_name",
              "dataType" : {
                "type" : "String"
              }
            } ]
          },
          "slug" : "out"
        } ],
        "isCustomOutputSchema" : false
      }
    },
    "stg_customers##xMQ3NwW7" : {
      "id" : "stg_customers##xMQ3NwW7",
      "component" : "TargetModel",
      "metadata" : {
        "label" : "stg_customers",
        "phase" : 0,
        "macroDependencies" : [ ]
      },
      "properties" : {
        "customQueryDisabled" : true,
        "customQuery" : false,
        "incrementalEditorDisabled" : true,
        "query" : "SELECT * \n\nFROM renamed\n",
        "incrementalKey" : false,
        "incremental" : {
          "expression" : "true"
        }
      },
      "ports" : {
        "inputs" : [ {
          "id" : "b12MZqoR",
          "schema" : {
            "providerType" : "Databricks",
            "fields" : [ {
              "name" : "customer_id",
              "dataType" : {
                "type" : "Integer"
              }
            }, {
              "name" : "first_name",
              "dataType" : {
                "type" : "String"
              }
            }, {
              "name" : "last_name",
              "dataType" : {
                "type" : "String"
              }
            } ]
          },
          "slug" : "renamed"
        } ],
        "outputs" : [ {
          "id" : "AlbIWcGb",
          "schema" : {
            "providerType" : "Databricks",
            "fields" : [ {
              "name" : "customer_id",
              "dataType" : {
                "type" : "Integer"
              }
            }, {
              "name" : "first_name",
              "dataType" : {
                "type" : "String"
              }
            }, {
              "name" : "last_name",
              "dataType" : {
                "type" : "String"
              }
            } ]
          },
          "slug" : "out"
        } ],
        "isCustomOutputSchema" : false
      }
    }
  },
  "connections" : [ {
    "id" : "XGVL1JRh",
    "source" : "source##YPp8aK9U",
    "sourcePort" : "SAWHdZ01",
    "target" : "renamed##udGLOQOW",
    "targetPort" : "KFQY13U2"
  }, {
    "id" : "c1sJMUMM",
    "source" : "renamed##udGLOQOW",
    "sourcePort" : "DUTyumng",
    "target" : "stg_customers##xMQ3NwW7",
    "targetPort" : "b12MZqoR"
  } ],
  "component" : "Model"
}